qase_xctest-1.0.4-py3.9-nspkg.pth
qaseio/xcode/__init__.py
qaseio/xcode/qase_exporter.py
qaseio/xcode/xcode_test_post_action.py
qaseio/xcreport/__init__.py
qaseio/xcreport/parser/__init__.py
qaseio/xcreport/parser/models/__init__.py
qaseio/xcreport/parser/models/action_abstract_test_summary.py
qaseio/xcreport/parser/models/action_record.py
qaseio/xcreport/parser/models/action_result.py
qaseio/xcreport/parser/models/action_test_activity_summary.py
qaseio/xcreport/parser/models/action_test_attachment.py
qaseio/xcreport/parser/models/action_test_metadata.py
qaseio/xcreport/parser/models/action_test_plan_run_summaries.py
qaseio/xcreport/parser/models/action_test_plan_run_summary.py
qaseio/xcreport/parser/models/action_test_summary.py
qaseio/xcreport/parser/models/action_test_summary_group.py
qaseio/xcreport/parser/models/action_test_summary_identifiable_object.py
qaseio/xcreport/parser/models/action_testable_summary.py
qaseio/xcreport/parser/models/actions_invocation_record.py
qaseio/xcreport/parser/models/helpers.py
qaseio/xcreport/parser/models/reference.py
qaseio/xcreport/parser/services/__init__.py
qaseio/xcreport/parser/services/xc_report_parser.py
qase_xctest-1.0.4.dist-info/AUTHORS.rst
qase_xctest-1.0.4.dist-info/LICENSE.txt
qase_xctest-1.0.4.dist-info/METADATA
qase_xctest-1.0.4.dist-info/WHEEL
qase_xctest-1.0.4.dist-info/entry_points.txt
qase_xctest-1.0.4.dist-info/namespace_packages.txt
qase_xctest-1.0.4.dist-info/top_level.txt
qase_xctest-1.0.4.dist-info/RECORD
