Metadata-Version: 2.1
Name: qase-xctest
Version: 1.0.4
Summary: Qase TMS
Home-page: https://github.com/qase-tms/qase-python/tree/master/qase-xctest
Author: Mikhail Golovko
Author-email: mihailmvg@gmail.com
License: apache
Platform: any
Classifier: Development Status :: 4 - Beta
Classifier: Programming Language :: Python
Requires-Python: >=3.6
License-File: LICENSE.txt
License-File: AUTHORS.rst
Requires-Dist: qaseio (<3.0,>=1.1.1)
Requires-Dist: attrs (>=19.3.0)
Provides-Extra: testing
Requires-Dist: pytest ; extra == 'testing'
Requires-Dist: pytest-cov ; extra == 'testing'
